media_profile_summaries_evaluation/bowlerhat.py
media_profile_summaries_evaluation/embeddings.py
media_profile_summaries_evaluation/extract.py
media_profile_summaries_evaluation/metrics.py
media_profile_summaries_evaluation/models.py
media_profile_summaries_evaluation-0.1.1.dist-info/METADATA
media_profile_summaries_evaluation-0.1.1.dist-info/WHEEL
media_profile_summaries_evaluation-0.1.1.dist-info/RECORD
