Metadata-Version: 2.1
Name: media-profile-summaries-evaluation
Version: 0.1.1
Summary: 
Author: Lewis Bails
Author-email: lewis.bails@ripjar.com
Requires-Python: >=3.9,<4.0
Classifier: Programming Language :: Python :: 3
Classifier: Programming Language :: Python :: 3.9
Classifier: Programming Language :: Python :: 3.10
Classifier: Programming Language :: Python :: 3.11
Requires-Dist: numpy (>=1.25.2,<2.0.0)
Requires-Dist: pydantic (>=2.3.0,<3.0.0)
Requires-Dist: requests (>=2.31.0,<3.0.0)
Requires-Dist: sentence-transformers (>=2.2.2,<3.0.0)
Requires-Dist: unidecode (>=1.3.6,<2.0.0)
